wg_easy_api/__init__.py
wg_easy_api/api.py
wg_easy_api/models.py
wg_easy_api/wg_easy.py
wg_easy_api-0.1.2.dist-info/LICENSE
wg_easy_api-0.1.2.dist-info/METADATA
wg_easy_api-0.1.2.dist-info/WHEEL
wg_easy_api-0.1.2.dist-info/RECORD
