Metadata-Version: 2.1
Name: wg-easy-api
Version: 0.1.2
Summary: API wrapper for wg-easy
Home-page: https://github.com/d0gied/wg-easy-api
License: MIT
Author: d0gied
Author-email: german.n.u@mail.ru
Requires-Python: >=3.12,<4.0
Classifier: License :: OSI Approved :: MIT License
Classifier: Programming Language :: Python :: 3
Classifier: Programming Language :: Python :: 3.12
Classifier: Programming Language :: Python :: 3.13
Requires-Dist: aiohttp (>=3.10.7,<4.0.0)
Requires-Dist: pydantic (>=2.9.2,<3.0.0)
Project-URL: Issues, https://github.com/d0gied/wg-easy-api/issues
Project-URL: Repository, https://github.com/d0gied/wg-easy-api
